search/__init__.py
search/main.py
search/main_search.py
search/search_google.py
search/search_yandex.py
web_searcher_cli-0.1.1.dist-info/METADATA
web_searcher_cli-0.1.1.dist-info/WHEEL
web_searcher_cli-0.1.1.dist-info/entry_points.txt
web_searcher_cli-0.1.1.dist-info/top_level.txt
web_searcher_cli-0.1.1.dist-info/RECORD
