Metadata-Version: 2.1
Name: web-searcher-cli
Version: 0.1.1
Summary: consosle web search from google or yandex
Home-page: https://github.com/gmanru/web_searcher_cli
Author: Gmvn
Author-email: mrgman11@yandex.ru
License: GNU General Public License v3.0
Keywords: json,google,yandex,bs4
Platform: UNKNOWN
